LICENSE
lightgbm_embedding/__init__.py
lightgbm_embedding-0.2.0.dist-info/LICENSE
lightgbm_embedding-0.2.0.dist-info/METADATA
lightgbm_embedding-0.2.0.dist-info/WHEEL
lightgbm_embedding-0.2.0.dist-info/RECORD
