Metadata-Version: 2.1
Name: lightgbm_embedding
Version: 0.2.0
Summary: Feature embeddings with LightGBM
License: MIT
Keywords: lightgbm,embeddings
Author: Atilla Karaahmetoğlu
Author-email: atilla.karaahmetoglu@gmail.com
Requires-Python: >=3.9,<3.14
Classifier: License :: OSI Approved :: MIT License
Classifier: Programming Language :: Python :: 3
Classifier: Programming Language :: Python :: 3.9
Classifier: Programming Language :: Python :: 3.10
Classifier: Programming Language :: Python :: 3.11
Classifier: Programming Language :: Python :: 3.12
Classifier: Programming Language :: Python :: 3.13
Classifier: Programming Language :: Python :: 3 :: Only
Requires-Dist: lightgbm
Requires-Dist: numpy (>=1.0.0,<2.0.0)
Requires-Dist: pandas (>=1.0.0,<2.0.0)
Requires-Dist: scikit-learn (>=1.0.0,<2.0.0)
Requires-Dist: scipy
